<Footprint name="MUB10A-M" >
  <Units type="mils" precision="3" />
  <Extents minX="-2508.5" minY="-2261" width="4067" height="3950" />
  <Padstack name="RX66Y13D0T" type="single" > 
    <Layers>
      <Layer name="TOP" >
        <Pad shape="rectangle" width="66" height="13" /> 
      </Layer>
      <Layer name="SOLDERMASK_TOP" >
        <Pad shape="rectangle" width="66" height="13" /> 
      </Layer>
      <Layer name="PASTEMASK_TOP" >
        <Pad shape="rectangle" width="66" height="13" /> 
      </Layer>
    </Layers>
  </Padstack>

  <Padstack name="RX66Y13D0T" type="single" > 
    <Layers>
      <Layer name="TOP" >
        <Pad shape="rectangle" width="66" height="13" /> 
      </Layer>
      <Layer name="SOLDERMASK_TOP" >
        <Pad shape="rectangle" width="66" height="13" /> 
      </Layer>
      <Layer name="PASTEMASK_TOP" >
        <Pad shape="rectangle" width="66" height="13" /> 
      </Layer>
    </Layers>
  </Padstack>
  <TextBlocks>
    <TextBlock name="17" width="6.25" height="25" lineSpacing="25" characterSpacing="6.25" /> 
  </TextBlocks>

  <Pins>
    <Pin number="1" padName="RX66Y13D0T" originX="-88.5" originY="39.3701" rotation="0" isMechanical="no" textBlockName="17" />
    <Pin number="2" padName="RX66Y13D0T" originX="-88.5" originY="19.685" rotation="0" isMechanical="no" textBlockName="17" />
    <Pin number="3" padName="RX66Y13D0T" originX="-88.5" originY="0" rotation="0" isMechanical="no" textBlockName="17" />
    <Pin number="4" padName="RX66Y13D0T" originX="-88.5" originY="-19.685" rotation="0" isMechanical="no" textBlockName="17" />
    <Pin number="5" padName="RX66Y13D0T" originX="-88.5" originY="-39.3701" rotation="0" isMechanical="no" textBlockName="17" />
    <Pin number="6" padName="RX66Y13D0T" originX="88.5" originY="-39.3701" rotation="0" isMechanical="no" textBlockName="17" />
    <Pin number="7" padName="RX66Y13D0T" originX="88.5" originY="-19.685" rotation="0" isMechanical="no" textBlockName="17" />
    <Pin number="8" padName="RX66Y13D0T" originX="88.5" originY="0" rotation="0" isMechanical="no" textBlockName="17" />
    <Pin number="9" padName="RX66Y13D0T" originX="88.5" originY="19.685" rotation="0" isMechanical="no" textBlockName="17" />
    <Pin number="10" padName="RX66Y13D0T" originX="88.5" originY="39.3701" rotation="0" isMechanical="no" textBlockName="17" />
  </Pins>
  <Vias>
  </Vias>
  <Layers>
    <Layer name="PACKAGE GEOMETRY/ASSEMBLY_TOP" packageHeight="43" >
      <Path lineWidth="0" type="line" >
        <Point x="-61" y="32.8701" />
        <Point x="-61" y="45.8701" />
      </Path>
    </Layer>
    <Layer name="PACKAGE GEOMETRY/ASSEMBLY_TOP" packageHeight="43" >
      <Path lineWidth="0" type="line" >
        <Point x="-61" y="45.8701" />
        <Point x="-99.5" y="45.8701" />
      </Path>
    </Layer>
    <Layer name="PACKAGE GEOMETRY/ASSEMBLY_TOP" packageHeight="43" >
      <Path lineWidth="0" type="line" >
        <Point x="-99.5" y="45.8701" />
        <Point x="-99.5" y="32.8701" />
      </Path>
    </Layer>
    <Layer name="PACKAGE GEOMETRY/ASSEMBLY_TOP" packageHeight="43" >
      <Path lineWidth="0" type="line" >
        <Point x="-99.5" y="32.8701" />
        <Point x="-61" y="32.8701" />
      </Path>
    </Layer>
    <Layer name="PACKAGE GEOMETRY/ASSEMBLY_TOP" packageHeight="43" >
      <Path lineWidth="0" type="line" >
        <Point x="-61" y="13.185" />
        <Point x="-61" y="26.185" />
      </Path>
    </Layer>
    <Layer name="PACKAGE GEOMETRY/ASSEMBLY_TOP" packageHeight="43" >
      <Path lineWidth="0" type="line" >
        <Point x="-61" y="26.185" />
        <Point x="-99.5" y="26.185" />
      </Path>
    </Layer>
    <Layer name="PACKAGE GEOMETRY/ASSEMBLY_TOP" packageHeight="43" >
      <Path lineWidth="0" type="line" >
        <Point x="-99.5" y="26.185" />
        <Point x="-99.5" y="13.185" />
      </Path>
    </Layer>
    <Layer name="PACKAGE GEOMETRY/ASSEMBLY_TOP" packageHeight="43" >
      <Path lineWidth="0" type="line" >
        <Point x="-99.5" y="13.185" />
        <Point x="-61" y="13.185" />
      </Path>
    </Layer>
    <Layer name="PACKAGE GEOMETRY/ASSEMBLY_TOP" packageHeight="43" >
      <Path lineWidth="0" type="line" >
        <Point x="-61" y="-6.5" />
        <Point x="-61" y="6.5" />
      </Path>
    </Layer>
    <Layer name="PACKAGE GEOMETRY/ASSEMBLY_TOP" packageHeight="43" >
      <Path lineWidth="0" type="line" >
        <Point x="-61" y="6.5" />
        <Point x="-99.5" y="6.5" />
      </Path>
    </Layer>
    <Layer name="PACKAGE GEOMETRY/ASSEMBLY_TOP" packageHeight="43" >
      <Path lineWidth="0" type="line" >
        <Point x="-99.5" y="6.5" />
        <Point x="-99.5" y="-6.5" />
      </Path>
    </Layer>
    <Layer name="PACKAGE GEOMETRY/ASSEMBLY_TOP" packageHeight="43" >
      <Path lineWidth="0" type="line" >
        <Point x="-99.5" y="-6.5" />
        <Point x="-61" y="-6.5" />
      </Path>
    </Layer>
    <Layer name="PACKAGE GEOMETRY/ASSEMBLY_TOP" packageHeight="43" >
      <Path lineWidth="0" type="line" >
        <Point x="-61" y="-26.185" />
        <Point x="-61" y="-13.185" />
      </Path>
    </Layer>
    <Layer name="PACKAGE GEOMETRY/ASSEMBLY_TOP" packageHeight="43" >
      <Path lineWidth="0" type="line" >
        <Point x="-61" y="-13.185" />
        <Point x="-99.5" y="-13.185" />
      </Path>
    </Layer>
    <Layer name="PACKAGE GEOMETRY/ASSEMBLY_TOP" packageHeight="43" >
      <Path lineWidth="0" type="line" >
        <Point x="-99.5" y="-13.185" />
        <Point x="-99.5" y="-26.185" />
      </Path>
    </Layer>
    <Layer name="PACKAGE GEOMETRY/ASSEMBLY_TOP" packageHeight="43" >
      <Path lineWidth="0" type="line" >
        <Point x="-99.5" y="-26.185" />
        <Point x="-61" y="-26.185" />
      </Path>
    </Layer>
    <Layer name="PACKAGE GEOMETRY/ASSEMBLY_TOP" packageHeight="43" >
      <Path lineWidth="0" type="line" >
        <Point x="-61" y="-45.8701" />
        <Point x="-61" y="-32.8701" />
      </Path>
    </Layer>
    <Layer name="PACKAGE GEOMETRY/ASSEMBLY_TOP" packageHeight="43" >
      <Path lineWidth="0" type="line" >
        <Point x="-61" y="-32.8701" />
        <Point x="-99.5" y="-32.8701" />
      </Path>
    </Layer>
    <Layer name="PACKAGE GEOMETRY/ASSEMBLY_TOP" packageHeight="43" >
      <Path lineWidth="0" type="line" >
        <Point x="-99.5" y="-32.8701" />
        <Point x="-99.5" y="-45.8701" />
      </Path>
    </Layer>
    <Layer name="PACKAGE GEOMETRY/ASSEMBLY_TOP" packageHeight="43" >
      <Path lineWidth="0" type="line" >
        <Point x="-99.5" y="-45.8701" />
        <Point x="-61" y="-45.8701" />
      </Path>
    </Layer>
    <Layer name="PACKAGE GEOMETRY/SILKSCREEN_TOP" packageHeight="43" >
      <Path lineWidth="0" type="shape" >
        <Point x="141.5" y="46.8701" />
        <Point x="141.5" y="31.8701" />
        <Point x="131.5" y="31.8701" />
        <Point x="131.5" y="46.8701" />
        <Point x="141.5" y="46.8701" />
      </Path>
    </Layer>
    <Layer name="PACKAGE GEOMETRY/ASSEMBLY_TOP" packageHeight="43" >
      <Path lineWidth="0" type="line" >
        <Point x="61" y="-32.8701" />
        <Point x="61" y="-45.8701" />
      </Path>
    </Layer>
    <Layer name="PACKAGE GEOMETRY/ASSEMBLY_TOP" packageHeight="43" >
      <Path lineWidth="0" type="line" >
        <Point x="61" y="-45.8701" />
        <Point x="99.5" y="-45.8701" />
      </Path>
    </Layer>
    <Layer name="PACKAGE GEOMETRY/ASSEMBLY_TOP" packageHeight="43" >
      <Path lineWidth="0" type="line" >
        <Point x="99.5" y="-45.8701" />
        <Point x="99.5" y="-32.8701" />
      </Path>
    </Layer>
    <Layer name="PACKAGE GEOMETRY/ASSEMBLY_TOP" packageHeight="43" >
      <Path lineWidth="0" type="line" >
        <Point x="99.5" y="-32.8701" />
        <Point x="61" y="-32.8701" />
      </Path>
    </Layer>
    <Layer name="PACKAGE GEOMETRY/ASSEMBLY_TOP" packageHeight="43" >
      <Path lineWidth="0" type="line" >
        <Point x="61" y="-13.185" />
        <Point x="61" y="-26.185" />
      </Path>
    </Layer>
    <Layer name="PACKAGE GEOMETRY/ASSEMBLY_TOP" packageHeight="43" >
      <Path lineWidth="0" type="line" >
        <Point x="61" y="-26.185" />
        <Point x="99.5" y="-26.185" />
      </Path>
    </Layer>
    <Layer name="PACKAGE GEOMETRY/ASSEMBLY_TOP" packageHeight="43" >
      <Path lineWidth="0" type="line" >
        <Point x="99.5" y="-26.185" />
        <Point x="99.5" y="-13.185" />
      </Path>
    </Layer>
    <Layer name="PACKAGE GEOMETRY/ASSEMBLY_TOP" packageHeight="43" >
      <Path lineWidth="0" type="line" >
        <Point x="99.5" y="-13.185" />
        <Point x="61" y="-13.185" />
      </Path>
    </Layer>
    <Layer name="PACKAGE GEOMETRY/ASSEMBLY_TOP" packageHeight="43" >
      <Path lineWidth="0" type="line" >
        <Point x="61" y="6.5" />
        <Point x="61" y="-6.5" />
      </Path>
    </Layer>
    <Layer name="PACKAGE GEOMETRY/ASSEMBLY_TOP" packageHeight="43" >
      <Path lineWidth="0" type="line" >
        <Point x="61" y="-6.5" />
        <Point x="99.5" y="-6.5" />
      </Path>
    </Layer>
    <Layer name="PACKAGE GEOMETRY/ASSEMBLY_TOP" packageHeight="43" >
      <Path lineWidth="0" type="line" >
        <Point x="99.5" y="-6.5" />
        <Point x="99.5" y="6.5" />
      </Path>
    </Layer>
    <Layer name="PACKAGE GEOMETRY/ASSEMBLY_TOP" packageHeight="43" >
      <Path lineWidth="0" type="line" >
        <Point x="99.5" y="6.5" />
        <Point x="61" y="6.5" />
      </Path>
    </Layer>
    <Layer name="PACKAGE GEOMETRY/ASSEMBLY_TOP" packageHeight="43" >
      <Path lineWidth="0" type="line" >
        <Point x="61" y="26.185" />
        <Point x="61" y="13.185" />
      </Path>
    </Layer>
    <Layer name="PACKAGE GEOMETRY/ASSEMBLY_TOP" packageHeight="43" >
      <Path lineWidth="0" type="line" >
        <Point x="61" y="13.185" />
        <Point x="99.5" y="13.185" />
      </Path>
    </Layer>
    <Layer name="PACKAGE GEOMETRY/ASSEMBLY_TOP" packageHeight="43" >
      <Path lineWidth="0" type="line" >
        <Point x="99.5" y="13.185" />
        <Point x="99.5" y="26.185" />
      </Path>
    </Layer>
    <Layer name="PACKAGE GEOMETRY/ASSEMBLY_TOP" packageHeight="43" >
      <Path lineWidth="0" type="line" >
        <Point x="99.5" y="26.185" />
        <Point x="61" y="26.185" />
      </Path>
    </Layer>
    <Layer name="PACKAGE GEOMETRY/ASSEMBLY_TOP" packageHeight="43" >
      <Path lineWidth="0" type="line" >
        <Point x="61" y="45.8701" />
        <Point x="61" y="32.8701" />
      </Path>
    </Layer>
    <Layer name="PACKAGE GEOMETRY/ASSEMBLY_TOP" packageHeight="43" >
      <Path lineWidth="0" type="line" >
        <Point x="61" y="32.8701" />
        <Point x="99.5" y="32.8701" />
      </Path>
    </Layer>
    <Layer name="PACKAGE GEOMETRY/ASSEMBLY_TOP" packageHeight="43" >
      <Path lineWidth="0" type="line" >
        <Point x="99.5" y="32.8701" />
        <Point x="99.5" y="45.8701" />
      </Path>
    </Layer>
    <Layer name="PACKAGE GEOMETRY/ASSEMBLY_TOP" packageHeight="43" >
      <Path lineWidth="0" type="line" >
        <Point x="99.5" y="45.8701" />
        <Point x="61" y="45.8701" />
      </Path>
    </Layer>
    <Layer name="PACKAGE GEOMETRY/PLACE_BOUND_TOP" packageHeight="43" packageHeightMin="2">
      <Path lineWidth="6" type="shape" >
        <Point x="-141.5" y="-53.2126" />
        <Point x="-141.5" y="53.2126" />
        <Point x="-81" y="53.2126" />
        <Point x="-81" y="81" />
        <Point x="81" y="81" />
        <Point x="81" y="53.2126" />
        <Point x="141.5" y="53.2126" />
        <Point x="141.5" y="-53.2126" />
        <Point x="81" y="-53.2126" />
        <Point x="81" y="-81" />
        <Point x="-81" y="-81" />
        <Point x="-81" y="-53.2126" />
        <Point x="-141.5" y="-53.2126" />
      </Path>
    </Layer>
    <Layer name="MANUFACTURING/NO_PROBE_TOP" packageHeight="43" >
      <Path lineWidth="6" type="shape" >
        <Point x="-156.5" y="-96" />
        <Point x="-156.5" y="96" />
        <Point x="156.5" y="96" />
        <Point x="156.5" y="-96" />
        <Point x="-156.5" y="-96" />
      </Path>
    </Layer>
    <Layer name="REF DES/SILKSCREEN_TOP" packageHeight="43" >
      <Label layer="REF DES/SILKSCREEN_TOP" textBlock="3" angle="0" x="0" y="-25" text="Ref" justify="center" />
    </Layer>
    <Layer name="DEVICE TYPE/SILKSCREEN_TOP" packageHeight="43" >
      <Label layer="DEVICE TYPE/SILKSCREEN_TOP" textBlock="3" angle="0" x="0" y="-25" text="Dev" justify="center" />
    </Layer>
    <Layer name="USER PART NUMBER/SILKSCREEN_TOP" packageHeight="43" >
      <Label layer="USER PART NUMBER/SILKSCREEN_TOP" textBlock="3" angle="0" x="0" y="-25" text="PN" justify="center" />
    </Layer>
    <Layer name="DEVICE TYPE/ASSEMBLY_TOP" packageHeight="43" >
      <Label layer="DEVICE TYPE/ASSEMBLY_TOP" textBlock="3" angle="0" x="0" y="-25" text="DEV" justify="center" />
    </Layer>
    <Layer name="COMPONENT VALUE/SILKSCREEN_TOP" packageHeight="43" >
      <Label layer="COMPONENT VALUE/SILKSCREEN_TOP" textBlock="3" angle="0" x="0" y="-25" text="VAL" justify="center" />
    </Layer>
    <Layer name="TOLERANCE/SILKSCREEN_TOP" packageHeight="43" >
      <Label layer="TOLERANCE/SILKSCREEN_TOP" textBlock="3" angle="0" x="0" y="-25" text="TOL" justify="center" />
    </Layer>
    <Layer name="REF DES/ASSEMBLY_TOP" packageHeight="43" >
      <Label layer="REF DES/ASSEMBLY_TOP" textBlock="3" angle="0" x="0" y="-25" text="Ref" justify="center" />
    </Layer>
    <Layer name="PACKAGE GEOMETRY/ASSEMBLY_TOP" packageHeight="43" >
      <Label layer="PACKAGE GEOMETRY/ASSEMBLY_TOP" textBlock="3" angle="0" x="-51" y="100.87" text="*" justify="center" />
    </Layer>
    <Layer name="PACKAGE GEOMETRY/SILKSCREEN_TOP" packageHeight="43" >
      <Label layer="PACKAGE GEOMETRY/SILKSCREEN_TOP" textBlock="3" angle="0" x="-98.5" y="125.87" text="*" justify="center" />
    </Layer>
    <Layer name="PACKAGE GEOMETRY/SILKSCREEN_TOP" packageHeight="43" >
      <Path lineWidth="6" type="line" >
        <Point x="-66" y="-66" />
        <Point x="66" y="-66" />
      </Path>
    </Layer>
    <Layer name="PACKAGE GEOMETRY/SILKSCREEN_TOP" packageHeight="43" >
      <Path lineWidth="6" type="line" >
        <Point x="66" y="-66" />
        <Point x="66" y="-58.9701" />
      </Path>
    </Layer>
    <Layer name="PACKAGE GEOMETRY/SILKSCREEN_TOP" packageHeight="43" >
      <Path lineWidth="6" type="line" >
        <Point x="66" y="66" />
        <Point x="-66" y="66" />
      </Path>
    </Layer>
    <Layer name="PACKAGE GEOMETRY/SILKSCREEN_TOP" packageHeight="43" >
      <Path lineWidth="6" type="line" >
        <Point x="-66" y="66" />
        <Point x="-66" y="58.9701" />
      </Path>
    </Layer>
    <Layer name="PACKAGE GEOMETRY/ASSEMBLY_TOP" packageHeight="43" >
      <Path lineWidth="0" type="line" >
        <Point x="-61" y="-61" />
        <Point x="61" y="-61" />
      </Path>
    </Layer>
    <Layer name="PACKAGE GEOMETRY/ASSEMBLY_TOP" packageHeight="43" >
      <Path lineWidth="0" type="line" >
        <Point x="61" y="-61" />
        <Point x="61" y="61" />
      </Path>
    </Layer>
    <Layer name="PACKAGE GEOMETRY/ASSEMBLY_TOP" packageHeight="43" >
      <Path lineWidth="0" type="line" >
        <Point x="61" y="61" />
        <Point x="-61" y="61" />
      </Path>
    </Layer>
    <Layer name="PACKAGE GEOMETRY/ASSEMBLY_TOP" packageHeight="43" >
      <Path lineWidth="0" type="line" >
        <Point x="-61" y="61" />
        <Point x="-61" y="-61" />
      </Path>
    </Layer>
    <Layer name="PACKAGE GEOMETRY/ASSEMBLY_TOP" packageHeight="43" >
      <Arc lineWidth="0" centerX="0" centerY="61" x1="-12" y1="61" x2="12" y2="61" startAngle="180" stopAngle="360" /> 
    </Layer>
    <Layer name="PACKAGE GEOMETRY/SILKSCREEN_TOP" packageHeight="43" >
      <Path lineWidth="6" type="line" >
        <Point x="-66" y="-58.9701" />
        <Point x="-66" y="-66" />
      </Path>
    </Layer>
    <Layer name="PACKAGE GEOMETRY/SILKSCREEN_TOP" packageHeight="43" >
      <Path lineWidth="6" type="line" >
        <Point x="66" y="58.9701" />
        <Point x="66" y="66" />
      </Path>
    </Layer>
  </Layers>
</Footprint>
